{
  "addedBy": "</types/users/Tom Carroll>",
  "addedOn": "2021-05-25T00:00:00.00-07:00",
  "authors": [
    "</types/authors/Matt Linderman>"
  ],
  "collections": {
    "</types/collections/Business/Entrepreneurship/Startups>": ""
  },
  "controller": "</types/users/Tom Carroll>",
  "description": "",
  "name": "Interview with CEO Peldi Guilizzoni about the growth of Balsamiq [Bootstrapped, profitable, and proud]",
  "path": "/Types/Web Pages/Interview with CEO Peldi Guilizzoni about the growth of Balsamiq [Bootstrapped, profitable, and proud]",
  "readBy": {
    "</types/users/Tom Carroll>": ""
  },
  "recommendations": {
    "</types/books/Eric Sink on the Business of Software>": "",
    "</types/books/Getting Real>": "",
    "</types/books/Micro ISV From Vision to Reality>": ""
  },
  "shortDescription": "",
  "url": "https://signalvnoise.com/posts/1733-interview-with-ceo-peldi-guilizzoni-about-the-growth-of-balsamiq-bootstrapped-profitable-and-proud"
}
