{
  "addedBy": "</types/users/Tom Carroll>",
  "addedOn": "2012-04-13T00:00:00.00-07:00",
  "collections": {
    "</types/collections/Business/Entrepreneurship>": ""
  },
  "controller": "</types/users/Tom Carroll>",
  "description": "",
  "name": "How the Ugliness of Google Reader Spawned a Booming Startup",
  "path": "/Types/Web Pages/How the Ugliness of Google Reader Spawned a Booming Startup",
  "readBy": {
    "</types/users/Tom Carroll>": ""
  },
  "shortDescription": "",
  "url": "http://www.fastcodesign.com/1664494/how-the-ugliness-of-google-reader-spawned-a-booming-start-up"
}