{
  "addedBy": "</types/users/Tom Carroll>",
  "addedOn": "2015-11-27T00:00:00.00-07:00",
  "collections": {
    "</types/collections/Business/Entrepreneurship/Startups/Ideas>": ""
  },
  "controller": "</types/users/Tom Carroll>",
  "description": "",
  "name": "Spotifys Design Lead on Why Side Projects Should Be Stupid",
  "notes": {
    "</types/notes/Spotifys Design Lead on Why Side Projects Should Be Stupid>": ""
  },
  "path": "/Types/Web Pages/Spotifys Design Lead on Why Side Projects Should Be Stupid",
  "readBy": {
    "</types/users/Tom Carroll>": ""
  },
  "shortDescription": "",
  "tags": {
    "</types/tags/Side projects>": ""
  },
  "title": "Spotify's Design Lead on Why Side Projects Should Be Stupid",
  "url": "http://firstround.com/review/Spotifys-Design-Lead-on-Why-Side-Projects-Should-be-Stupid/"
}
