{
  "addedBy": "</types/users/Tom Carroll>",
  "addedOn": "2012-11-12T00:00:00.00-07:00",
  "authors": [
    "</types/authors/James Betteley>"
  ],
  "collections": {
    "</types/collections/Computer Science/Software Engineering/DevOps>": "",
    "</types/collections/Projects/Things to Check Out>": ""
  },
  "controller": "</types/users/Tom Carroll>",
  "description": "",
  "name": "Deployment Automation Patterns",
  "path": "/Types/Documents/Deployment Automation Patterns",
  "shortDescription": ""
}
