{
  "addedBy": "</types/users/Tom Carroll>",
  "addedOn": "2013-06-17T00:00:00.00-07:00",
  "collections": {
    "</types/collections/Business/Career Management>": ""
  },
  "controller": "</types/users/Tom Carroll>",
  "description": "",
  "name": "The Only Way to Raise Your Salary",
  "path": "/Types/Web Pages/The Only Way to Raise Your Salary",
  "readBy": {
    "</types/users/Tom Carroll>": ""
  },
  "shortDescription": "",
  "url": "https://www.linkedin.com/today/post/article/20130617180159-36052017-the-only-way-to-raise-your-salary?trk=tod-home-art-large_0"
}