{
  "addedBy": "</types/users/Tom Carroll>",
  "addedOn": "2012-04-13T00:00:00.00-07:00",
  "collections": {
    "</types/collections/Business/Entrepreneurship>": ""
  },
  "controller": "</types/users/Tom Carroll>",
  "description": "",
  "feeds": {
    "</types/feeds/TechCrunch>": ""
  },
  "name": "Another Y Combinator Win: WuFoo Exits for $35 Million, After Raising Only $118,000",
  "path": "/Types/Web Pages/Another Y Combinator Win: WuFoo Exits for $35 Million, After Raising Only $118,000",
  "readBy": {
    "</types/users/Tom Carroll>": ""
  },
  "shortDescription": "",
  "url": "http://techcrunch.com/2011/04/25/wufoo-35-million-surveymonkey/"
}