{
  "addedBy": "</types/users/Tom Carroll>",
  "addedOn": "2018-01-15T00:00:00.00-07:00",
  "authors": [
    "</types/authors/Hoa Loranger>",
    "</types/authors/Jakob Nielsen>"
  ],
  "collections": {
    "</types/collections/Computer Science/Human Computer Interaction/User Experience/Design>": "",
    "</types/collections/Writing>": ""
  },
  "controller": "</types/users/Tom Carroll>",
  "description": "",
  "name": "Microcontent: A Few Small Words Have a Mega Impact on Business",
  "notes": {
    "</types/notes/Microcontent A Few Small Words Have a Mega Impact on Business>": ""
  },
  "path": "/Types/Web Pages/Microcontent: A Few Small Words Have a Mega Impact on Business",
  "shortDescription": "",
  "url": "https://www.nngroup.com/articles/microcontent-how-to-write-headlines-page-titles-and-subject-lines/"
}