{
  "addedBy": "</types/users/Tom Carroll>",
  "addedOn": "2017-04-02T00:00:00.00-07:00",
  "controller": "</types/users/Tom Carroll>",
  "description": "",
  "name": "Usability Engineering Book",
  "path": "/Types/Pictures/Usability Engineering Book",
  "pictureOf": {
    "</types/books/Usability Engineering>": ""
  },
  "representations": {
    "usability_engineering_book_cover_large.jpg.lnk.json": "",
    "usability_engineering_book_cover_medium.jpg.lnk.json": "",
    "usability_engineering_book_cover_preview.jpg.lnk.json": "",
    "usability_engineering_book_cover_small.jpg.lnk.json": ""
  },
  "shortDescription": ""
}