{
  "addedBy": "</types/users/Tom Carroll>",
  "addedOn": "2012-04-13T00:00:00.00-07:00",
  "children": {
    "</types/webPages/Choosing a Minimally Viable Cofounder>": "",
    "</types/webPages/Important Questions Startup Cofounders Should Ask Each Other>": ""
  },
  "collections": {
    "</types/collections/Business/Entrepreneurship/Startups>": ""
  },
  "controller": "</types/users/Tom Carroll>",
  "description": "",
  "name": "Finding Cofounders",
  "path": "/Types/Collections/Business/Entrepreneurship/Startups/Finding Cofounders",
  "shortDescription": "Things regarding finding co-founders for new businesses (start-ups)."
}
