{
  "addedBy": "</types/users/Tom Carroll>",
  "addedOn": "2014-01-01T00:00:00.00-07:00",
  "authors": [
    "</types/authors/Jenna Curry>"
  ],
  "collections": {
    "</types/collections/Computer Science/Human Computer Interaction/User Experience/Design>": "",
    "</types/collections/Art and Design/Typography>": ""
  },
  "controller": "</types/users/Tom Carroll>",
  "description": "",
  "name": "What You Should Know About Web Typography That Will Make You A Better Designer",
  "path": "/Types/Web Pages/What You Should Know About Web Typography That Will Make You A Better Designer",
  "readBy": {
    "</types/users/Tom Carroll>": ""
  },
  "shortDescription": "",
  "url": "http://abetteruserexperience.com/2013/02/what-you-should-know-about-web-typography-that-will-make-you-a-better-designer/"
}